{"data_mtime": 1648149530, "dep_lines": [1, 2, 3, 4, 23, 1], "dep_prios": [10, 10, 5, 5, 5, 5], "dependencies": ["sys", "types", "abc", "typing", "typing_extensions", "builtins"], "hash": "e13fba09edb87e0b1592465d78f1a6ef3fdbe28e64d526416a11aeaf0b594e4e", "id": "codecs", "ignore_all": true, "interface_hash": "b2a9453e62337b24311bd45ea7d4d0126e677535136fd058d4ee7cca88f1ce4b", "mtime": 1647864535, "options": {"allow_redefinition": false, "allow_untyped_globals": false, "always_false": [], "always_true": [], "bazel": false, "check_untyped_defs": false, "disallow_any_decorated": false, "disallow_any_explicit": false, "disallow_any_expr": false, "disallow_any_generics": false, "disallow_any_unimported": false, "disallow_incomplete_defs": false, "disallow_subclassing_any": false, "disallow_untyped_calls": false, "disallow_untyped_decorators": false, "disallow_untyped_defs": false, "follow_imports": "normal", "follow_imports_for_stubs": false, "ignore_errors": false, "ignore_missing_imports": true, "implicit_reexport": true, "local_partial_types": false, "mypyc": false, "no_implicit_optional": true, "platform": "linux", "plugins": ["airflow.mypy.plugin.decorators"], "show_none_errors": true, "strict_equality": false, "strict_optional": true, "strict_optional_whitelist": null, "warn_no_return": true, "warn_return_any": false, "warn_unreachable": false, "warn_unused_ignores": false}, "path": "/usr/local/lib/python3.7/site-packages/mypy/typeshed/stdlib/codecs.pyi", "plugin_data": null, "size": 12435, "suppressed": [], "version_id": "0.910"}